IsMyInternetWorking/__init__.py
IsMyInternetWorking/__main__.py
IsMyInternetWorking-0.2.1.dist-info/LICENSE.txt
IsMyInternetWorking-0.2.1.dist-info/METADATA
IsMyInternetWorking-0.2.1.dist-info/WHEEL
IsMyInternetWorking-0.2.1.dist-info/top_level.txt
IsMyInternetWorking-0.2.1.dist-info/RECORD
