Metadata-Version: 2.1
Name: IsMyInternetWorking
Version: 0.2.1
Summary: Console-based recreation of the function of ismyinternetworking.com's website.
Author-email: Alaester Nikolai Modern <a.modern.freelancing@gmail.com>
Project-URL: Homepage, https://github.com/Lil-Allie-Astra/IsMyInternetWorking
Project-URL: Bug Tracker, https://github.com/Lil-Allie-Astra/IsMyInternetWorking/issues
Classifier: Programming Language :: Python :: 3
Classifier: License :: OSI Approved :: GNU Affero General Public License v3
Classifier: Operating System :: OS Independent
Requires-Python: >=3.9
License-File: LICENSE.txt
